docs
htmlcov
sphinxcontrib
tests
