Metadata-Version: 2.1
Name: sphinxcontrib-shtest
Version: 0.3.0
Home-page: https://github.com/tillahoffmann/sphinxcontrib-shtest
